fd_component/__init__.py
fd_component/frontend/build/asset-manifest.json
fd_component/frontend/build/bootstrap.min.css
fd_component/frontend/build/index.html
fd_component/frontend/build/precache-manifest.9d79e382e67b0ea743cf5e41e98e4fed.js
fd_component/frontend/build/service-worker.js
fd_component/frontend/build/static/css/2.2bdbc9a0.chunk.css
fd_component/frontend/build/static/css/2.2bdbc9a0.chunk.css.map
fd_component/frontend/build/static/js/2.becb3afd.chunk.js
fd_component/frontend/build/static/js/2.becb3afd.chunk.js.LICENSE.txt
fd_component/frontend/build/static/js/2.becb3afd.chunk.js.map
fd_component/frontend/build/static/js/main.ca9b5d10.chunk.js
fd_component/frontend/build/static/js/main.ca9b5d10.chunk.js.map
fd_component/frontend/build/static/js/runtime-main.44d30fc2.js
fd_component/frontend/build/static/js/runtime-main.44d30fc2.js.map
fd_component/frontend/build/static/media/alfa-slab-one-all-400-normal.5772fe44.woff
fd_component/frontend/build/static/media/alfa-slab-one-latin-400-normal.8c51df77.woff2
fd_component/frontend/build/static/media/alfa-slab-one-latin-ext-400-normal.f99f4079.woff2
fd_component/frontend/build/static/media/alfa-slab-one-vietnamese-400-normal.f559bdf3.woff2
fd_component/frontend/build/static/media/background.da6590e4.png
fd_component/frontend/build/static/media/fd_symbol.090d39dc.png
fd_component-0.0.1.dist-info/LICENSE
fd_component-0.0.1.dist-info/METADATA
fd_component-0.0.1.dist-info/WHEEL
fd_component-0.0.1.dist-info/top_level.txt
fd_component-0.0.1.dist-info/RECORD
